DISCOMPUTIFY/__init__.py
DISCOMPUTIFY/__main__.py
DISCOMPUTIFY/BASE_PROGRAM/__init__.py
DISCOMPUTIFY/BASE_PROGRAM/base_program.py
DISCOMPUTIFY/CLIENT_NODE/__init__.py
DISCOMPUTIFY/CLIENT_NODE/client_node.py
DISCOMPUTIFY/COMPUTING_NODE/__init__.py
DISCOMPUTIFY/COMPUTING_NODE/computing_node.py
DISCOMPUTIFY/FTP_NODE/__init__.py
DISCOMPUTIFY/FTP_NODE/ftp_node.py
DISCOMPUTIFY/MASTER_NODE/__init__.py
DISCOMPUTIFY/MASTER_NODE/master_node.py
discomputify_P_Y_R_O_B_O_T-1.0.0.dist-info/LICENSE
discomputify_P_Y_R_O_B_O_T-1.0.0.dist-info/METADATA
discomputify_P_Y_R_O_B_O_T-1.0.0.dist-info/WHEEL
discomputify_P_Y_R_O_B_O_T-1.0.0.dist-info/top_level.txt
discomputify_P_Y_R_O_B_O_T-1.0.0.dist-info/RECORD
