Metadata-Version: 2.1
Name: discomputify-P-Y-R-O-B-O-T
Version: 1.0.0
Summary: A LIBRARY FOR DISTRIBUTED COMPUTING IN PYTHON
Author-email: KUSHAL <NONE@NONE.com>
License: GNU GENERAL PUBLIC LICENSE
Project-URL: Homepage, https://github.com/P-Y-R-O-B-O-T/DISCOMPUTIFY
Keywords: distributed,computing,distributed computing,machine learning,cluster computing,cluster
Requires-Python: >=3.10
License-File: LICENSE
Requires-Dist: cypher-protocol-P-Y-R-O-B-O-T
